fastpy_cli/__init__.py
fastpy_cli/ai.py
fastpy_cli/config.py
fastpy_cli/logger.py
fastpy_cli/main.py
fastpy_cli/setup.py
fastpy_cli/utils.py
fastpy_cli/libs/__init__.py
fastpy_cli/libs/cache/__init__.py
fastpy_cli/libs/cache/drivers.py
fastpy_cli/libs/cache/facade.py
fastpy_cli/libs/cache/manager.py
fastpy_cli/libs/encryption/__init__.py
fastpy_cli/libs/encryption/encrypter.py
fastpy_cli/libs/encryption/facade.py
fastpy_cli/libs/events/__init__.py
fastpy_cli/libs/events/dispatcher.py
fastpy_cli/libs/events/facade.py
fastpy_cli/libs/hashing/__init__.py
fastpy_cli/libs/hashing/facade.py
fastpy_cli/libs/hashing/hasher.py
fastpy_cli/libs/hashing/manager.py
fastpy_cli/libs/http/__init__.py
fastpy_cli/libs/http/client.py
fastpy_cli/libs/http/facade.py
fastpy_cli/libs/mail/__init__.py
fastpy_cli/libs/mail/drivers.py
fastpy_cli/libs/mail/facade.py
fastpy_cli/libs/mail/mailer.py
fastpy_cli/libs/notifications/__init__.py
fastpy_cli/libs/notifications/channels.py
fastpy_cli/libs/notifications/facade.py
fastpy_cli/libs/notifications/manager.py
fastpy_cli/libs/notifications/notification.py
fastpy_cli/libs/queue/__init__.py
fastpy_cli/libs/queue/drivers.py
fastpy_cli/libs/queue/facade.py
fastpy_cli/libs/queue/job.py
fastpy_cli/libs/queue/manager.py
fastpy_cli/libs/storage/__init__.py
fastpy_cli/libs/storage/drivers.py
fastpy_cli/libs/storage/facade.py
fastpy_cli/libs/storage/manager.py
fastpy_cli/libs/support/__init__.py
fastpy_cli/libs/support/config.py
fastpy_cli/libs/support/container.py
fastpy_cli/libs/support/facade.py
fastpy_cli-1.2.16.dist-info/licenses/LICENSE
fastpy_cli-1.2.16.dist-info/METADATA
fastpy_cli-1.2.16.dist-info/WHEEL
fastpy_cli-1.2.16.dist-info/entry_points.txt
fastpy_cli-1.2.16.dist-info/top_level.txt
fastpy_cli-1.2.16.dist-info/RECORD
