Metadata-Version: 2.4
Name: fastpy-cli
Version: 1.2.16
Summary: Create production-ready FastAPI projects with one command
Author-email: Vutia Enterprise <hello@ve.ke>
Maintainer-email: Vutia Enterprise <hello@ve.ke>
License: MIT
Project-URL: Homepage, https://fastpy.ve.ke
Project-URL: Documentation, https://fastpy.ve.ke
Project-URL: Repository, https://github.com/vutia-ent/fastpy-cli
Project-URL: Issues, https://github.com/vutia-ent/fastpy-cli/issues
Project-URL: Changelog, https://github.com/vutia-ent/fastpy-cli/blob/main/CHANGELOG.md
Keywords: fastapi,cli,project-template,sqlmodel,python,api,rest,jwt,authentication,code-generator,ai
Classifier: Development Status :: 4 - Beta
Classifier: Environment :: Console
Classifier: Framework :: FastAPI
Classifier: Intended Audience :: Developers
Classifier: License :: OSI Approved :: MIT License
Classifier: Operating System :: OS Independent
Classifier: Programming Language :: Python :: 3
Classifier: Programming Language :: Python :: 3.9
Classifier: Programming Language :: Python :: 3.10
Classifier: Programming Language :: Python :: 3.11
Classifier: Programming Language :: Python :: 3.12
Classifier: Programming Language :: Python :: 3.13
Classifier: Topic :: Software Development :: Code Generators
Classifier: Topic :: Internet :: WWW/HTTP :: HTTP Servers
Classifier: Typing :: Typed
Requires-Python: >=3.9
License-File: LICENSE
Requires-Dist: typer>=0.9.0
Requires-Dist: rich>=13.0.0
Requires-Dist: httpx>=0.25.0
Requires-Dist: tomli>=2.0.0; python_version < "3.11"
Requires-Dist: toml>=0.10.0
Provides-Extra: dev
Requires-Dist: pytest>=7.0.0; extra == "dev"
Requires-Dist: pytest-cov>=4.0.0; extra == "dev"
Requires-Dist: pytest-mock>=3.10.0; extra == "dev"
Requires-Dist: black>=23.0.0; extra == "dev"
Requires-Dist: ruff>=0.1.0; extra == "dev"
Requires-Dist: mypy>=1.0.0; extra == "dev"
Requires-Dist: respx>=0.20.0; extra == "dev"
Dynamic: license-file
